py2java/PythonToJava.py
py2java/__init__.py
py2java-0.0.11.dist-info/METADATA
py2java-0.0.11.dist-info/WHEEL
py2java-0.0.11.dist-info/top_level.txt
py2java-0.0.11.dist-info/RECORD
